irods2dataverse/__init__.py
irods2dataverse/avu2json.py
irods2dataverse/cli_input.py
irods2dataverse/customClass.py
irods2dataverse/direct_upload.py
irods2dataverse/from_irods.py
irods2dataverse/metadatablocks.py
irods2dataverse/to_dataverse.py
irods2dataverse/userScript.py
irods2dataverse-0.0.4.dist-info/licenses/LICENSE
irods2dataverse-0.0.4.dist-info/METADATA
irods2dataverse-0.0.4.dist-info/WHEEL
irods2dataverse-0.0.4.dist-info/top_level.txt
irods2dataverse-0.0.4.dist-info/RECORD
