Metadata-Version: 2.4
Name: irods2dataverse
Version: 0.0.4
Summary: Tag and push datasets from iRODS to a dataverse installation
Author-email: Danai Kafetzaki <danai.kafetzaki@kuleuven.be>, Joachim Bovin <joachim.bovin@kuleuven.be>, Mariana Montes <mariana.montes@kuleuven.be>
License: MIT License
Project-URL: repository, https://github.com/kuleuven/iRODS-Dataverse
Requires-Python: >=3.10
License-File: LICENSE
Requires-Dist: configparser==7.1.0
Requires-Dist: exceptiongroup==1.2.1
Requires-Dist: mango-mdschema==1.0.2
Requires-Dist: maskpass==0.3.7
Requires-Dist: pyDataverse==0.3.2
Requires-Dist: python-magic==0.4.27
Requires-Dist: requests==2.31.0
Requires-Dist: rich==13.9.4
Requires-Dist: typing-extensions==4.11.0
Provides-Extra: dev
Dynamic: license-file
